fw_gear_file_esign/__init__.py
fw_gear_file_esign/bin/encode_key.py
fw_gear_file_esign/bin/keygen.py
fw_gear_file_esign/bin/verify_file.py
fw_gear_file_esign/main.py
fw_gear_file_esign/mfa_client.py
fw_gear_file_esign/parser.py
fw_gear_file_esign/utils.py
fw_gear_file_esign-0.1.1.dist-info/LICENSE
fw_gear_file_esign-0.1.1.dist-info/METADATA
fw_gear_file_esign-0.1.1.dist-info/WHEEL
fw_gear_file_esign-0.1.1.dist-info/RECORD
