Metadata-Version: 2.1
Name: fw-gear-file-esign
Version: 0.1.1
Summary: file-esign is a gear for e-signing plaintext and pdf files. It uses MFA to authenticate the user and incorporates identity and timestamp into an e-signature of the file.
Home-page: https://gitlab.com/flywheel-io/scientific-solutions/gears/file-esign
License: MIT
Keywords: Flywheel,Gears
Author: Flywheel
Author-email: support@flywheel.io
Requires-Python: >=3.11,<4.0
Classifier: License :: OSI Approved :: MIT License
Classifier: Programming Language :: Python :: 3
Classifier: Programming Language :: Python :: 3.11
Classifier: Programming Language :: Python :: 3.12
Classifier: Topic :: Scientific/Engineering
Requires-Dist: backoff (>=2.2.1,<3.0.0)
Requires-Dist: cryptography (>=43.0.1,<44.0.0)
Requires-Dist: flywheel-gear-toolkit (>=0.6,<0.7)
Requires-Dist: flywheel-sdk (>=18,<19)
Requires-Dist: pikepdf (>=9.2.1,<10.0.0)
Requires-Dist: twilio (>=9.3.2,<10.0.0)
Project-URL: Repository, https://gitlab.com/flywheel-io/scientific-solutions/gears/file-esign
